tool_goto_window/__init__.py
tool_goto_window/cli.py
tool_goto_window/config.py
tool_goto_window/main.py
tool_goto_window/py.typed
tool_goto_window-0.1.4.dist-info/METADATA
tool_goto_window-0.1.4.dist-info/WHEEL
tool_goto_window-0.1.4.dist-info/entry_points.txt
tool_goto_window-0.1.4.dist-info/RECORD
