Metadata-Version: 2.4
Name: tool-goto-window
Version: 0.1.4
Summary: A CLI tool to switch between windows
Author-email: Eyal Levin <eyalev@gmail.com>
Requires-Python: >=3.12
Requires-Dist: pywinctl
Requires-Dist: toml
Requires-Dist: typer
